qjoin/__init__.py
qjoin/logger.py
qjoin/main.py
qjoin-0.1.0.dist-info/LICENSE
qjoin-0.1.0.dist-info/METADATA
qjoin-0.1.0.dist-info/WHEEL
qjoin-0.1.0.dist-info/RECORD
