Metadata-Version: 2.1
Name: qjoin
Version: 0.1.0
Summary: qjoin is a data manipulation library that provides simple and efficient joining and collection processing functionality
License: MIT
Author: Fabien Arcellier
Author-email: fabien.arcellier@gmail.com
Requires-Python: >=3.8,<4.0
Classifier: Intended Audience :: Developers
Classifier: License :: OSI Approved :: MIT License
Classifier: Operating System :: OS Independent
Classifier: Programming Language :: Python :: 3
Classifier: Programming Language :: Python :: 3.8
Classifier: Programming Language :: Python :: 3.9
Classifier: Programming Language :: Python :: 3.10
Classifier: Programming Language :: Python :: 3.11
Project-URL: Chat, https://discord.gg/nMn9YPRGSY
Project-URL: Documentation, https://qjoin.readthedocs.io/en/latest/
Project-URL: Issue Tracker, https://github.com/FabienArcellier/qjoin/issues
Project-URL: Source code, https://github.com/FabienArcellier/qjoin
